vval/__init__.py
vval/vval.py
vval-2.1.8.dist-info/LICENSE
vval-2.1.8.dist-info/METADATA
vval-2.1.8.dist-info/WHEEL
vval-2.1.8.dist-info/top_level.txt
vval-2.1.8.dist-info/RECORD
