Metadata-Version: 2.1
Name: vval
Version: 2.1.8
Summary: Input validation in Python
Home-page: https://github.com/munozarturo/vval
Author: Arturo Munoz
Author-email: munoz.arturoroman@gmail.com
Project-URL: Bug Reports, https://github.com/munozarturo/vval/issues
Project-URL: Source, https://github.com/munozarturo/vval/
Keywords: validation
Classifier: Intended Audience :: Developers
Classifier: License :: OSI Approved :: MIT License
Classifier: Programming Language :: Python :: 3
Classifier: Programming Language :: Python :: 3.11
Classifier: Programming Language :: Python :: 3.12
Classifier: Operating System :: OS Independent
Classifier: Topic :: Software Development :: Libraries :: Python Modules
Requires-Python: >=3.11
License-File: LICENSE
Requires-Dist: varname ==0.11.0
Requires-Dist: typing-inspect ==0.8.0
Provides-Extra: dev
Requires-Dist: pytest ; extra == 'dev'
Requires-Dist: mypy ; extra == 'dev'
Requires-Dist: pytest-cov ; extra == 'dev'
Requires-Dist: flake8 ; extra == 'dev'
Requires-Dist: black ; extra == 'dev'
Provides-Extra: docs
Requires-Dist: sphinx ; extra == 'docs'
Requires-Dist: sphinx-rtd-theme ; extra == 'docs'
